{
    "adventistaBrasil":"Adventista Brasil",
    "adventistaSudamerica":"Adventista Sudamerica",
    "allAbout":"All About",
    "andreFernandes":"André Fernandes",
    "automotor":"Automotor",
    "biaFigueiredo":"Bia Figueiredo",
    "brunetCast":"BrunetCast",
    "camilaBarros":"Camila Barros",
    "cassioCortes":"Cassio Cortes",
    "daystar":"Daystar Espanhol",
    "deiveLeonardo":"Deive Leonardo",
    "flavioGomes":"Flavio Gomes",
    "formulaIndy":"Formula Indy",
    "grandePremio":"Grande Premio",
    "grandePremioF1":"Grande Premio F1",
    "grandePremio2":"Grande Premio 2",
    "hernandesDiasLopes":"Hernandes Dias Lopes",
    "IGIPP":"IPP TV",
    "itatiaia":"Itatiaia",
    "itatiaiaEsporte":"Itatiaia Esporte",
    "oTempo":"O Tempo",
    "oTempoSports":"O Tempo Sports",
    "rodrigoSilva":"Rodrigo Silva",
    "sabeTodo":"Sabe Todo",
    "tiagoBrunet":"Tiago Brunet",
    "tvACritica":"TV A Crítica",
    "arivalDiasCasimiro":"Arival Dias Casimiro",
    "cornelioAugusto":"Pr. Cornélio Augusto",
    "cleitonPinheiro":"Cleiton Pinheiro",
    "regenere":"Ministério Regenere",
    "drPet":"Alexandre Rossi Dr. Pet",
    "embrulhaPraViagem":"Embrulha Pra Viagem",
    "helenaTannure":"Helena Tannure",
    "igrejaDaCidade":"Igreja da Cidade Online",
    "PIBCuritiba":"PIB Curitiba",
    "danielBrunet":"Daniel Brunet",
    "deusEAmor":"Deus é Amor",
    "josueBrandao":"Josué Brandão",
    "lagoinhaTV":"Lagoinha TV",
    "popBola":"Pop Bola Esporte Clube",
    "edmeiaWilliams":"Edméia Williams",
    "carlosMaia":"Carlos Maia",
    "cortesJesusCopy":"Cortes JesusCopy",
    "familiaJesusCopy":"Familia JesusCopy",
    "feNoDiva":"Fé no Divã",
    "galoTV":"Galo TV",
    "emOFF":"Canal EM OFF",
    "elegante":"Elegante",
    "seLigaNaNoticia":"Se Liga Na Notícia",
    "inssSemSegredo":"INSS Sem Segredo",
    "inssPassoAPasso":"INSS Passo a Passo",
    "futshow":"FutShowOficial",
    "sabeTudo":"Sabe Tudo",
    "apaixonadosPorEstrada":"Apaixonados por Estrada",
    "sagaScreen":"Saga Screen",
    "sabeTudoMundo":"Sabe Tudo Mundo",
    "eraUmaVez":"Era Uma Vez",
    "futebolMais":"Futebol e Mais",
    "gospelHits":"Gospel Hits",
    "gospelTrends":"Gospel Trends",
    "poderSalvacao":"Poder & Salvação",
    "centralDaPalavra":"Central da Palavra",
    "promessaBencao":"Promessa e Benção",
    "amoViverPraCristo":"Amo Viver Para Cristo",
    "vidaDeFe":"Vida de Fé",
    "palavrasDeFe":"Palavra de Fé",
    "3PalavrinhasBaby":"3Palavrinhas Baby",
    "IPB":"Igreja Presbiteriana do Brasil",
    "verdadeVida":"Verdade e Vida",
    "itatiaiaPatrulha":"Itatiaia Patrulha",
    "itatiaiaSaude":"Itatiaia Saúde",
    "itatiaiaGastro":"Itatiaia Gastrô",
    "talithaPereira":"Talitha Pereira",
    "newCreationTV":"New Creation TV Português",
    "corinthians":"Corinthians Esports",
    "cristaMundial":"Cristã Mundial",
    "igrejaDoAmor":"Igreja do Amor",
    "casaDeDestino":"Casa de Destino",
    "jesusCopy":"JesusCopy",
    "churchOfTheCity":"Church of the City",
    "deiveLeonardoEnglish":"Deive Leonardo English",
    "sagaWrestling":"Saga Wrestling",
    "sagaSoccer":"Saga Soccer",
    "sagaSuccess":"Saga Success",
    "oAntagonista":"O Antagonista",
    "tecGol":"TECGOL",
    "litoCavalcanti":"Lito Cavalcanti",
    "CNNEconomia":"CNN Brasil Economia",
    "CNNPop":"CNN Pop",
    "CNNViagemGastronomia":"CNN Viagem & Gastronomia",
    "CNNEsportes":"CNN Esportes",
    "assembleiaMG":"Assembléia de Minas Gerais",
    "CNN":"CNN Brasil",
    "lagoinhaBrasilia":"Lagoinha Brasília Capital",
    "botecoF1":"Boteco F1",
    "ivanMaia":"Ivan Maia Treinamentos",
    "radioNovasdePaz":"Rádio Novas de Paz Oficial",
    "NOVASDEPAZ":"NOVASDEPAZOFICIAL",
    "profetaRonny":"Profeta Ronny Oliveira",
    "donosDaBola":"Donos da Bola",
    "noAlvo":"NoAlvo",
    "willsong":"Willsong",
    "livesAtlantida":"Lives Atlântida",
    "pretinhoBasico":"Pretinho Básico",
    "olharDigital":"Olhar Digital",
    "GZH":"GZH",
    "bolaNasCostas":"O Bola Nas Costas",
    "ATLTV":"ATL TV",
    "ADVEC":"ADVEC",
    "santoFlow":"SantoFlow Podcast",
    "ADSeara":"AD Seara Oficial",
    "105FM":"105 FM Futebol Club",
    "tvEncontroComCristo":"TV Encontro com Cristo",
    "firstBaptistDallas":"First Baptist Dallas",
    "sergioFreitas":"Sergio Freitas",
    "luizaPossi":"Luiza Possi",
    "leoDiasTV":"Leo Dias TV",
    "ensinandoSiao":"Ministério Ensinando de Sião",
    "atitudeTV":"Atitude TV",
    "novosComecos":"Novos Começos TV",
    "rebecaNemer":"Rebeca Nemer",
    "glauciaOliveira":"Glaucia Oliveira",
    "pbShorts":"PB Shorts",
    "josephPrince":"Joseph Prince",
    "alemDoGol":"Além do Gol",
    "canalCidadaoBrasileiro":"Canal do Cidadão Brasileiro",
    "programaFolego":"Programa Fôlego",
    "casaDeDeus":"Igreja Batista Casa de Deus",
    "marceloRossi":"Padre Marcelo Rossi",
    "somethingGood":"Something Good",
    "brasilParalelo":"Brasil Paralelo",
    "neoFeed":"NeoFeed Brasil",
    "tvAparecida":"TV Aparecida",
    "timesBrasil":"Time Brasil",
    "advogadoRoberto":"Advogado e Professor Roberto Conceição",
    "diarioDoTrabalhador":"Diario do Trabalhador",
    "tenhoDireito":"Tenho Direito?",
    "tvDoZe":"TV do Zé",
    "radioSalvador":"Rádio Salvador FM",
    "ATLShorts":"ATL Shorts",
    "lance":"Lance!",
    "rasgandoOsCeus":"Igreja Rasgando os Céus",
    "authenticGames":"Authentic Games",
    "ronJones":"Ron Jones",
    "feliz7Kids":"Feliz 7 Kids",
    "adAlpha":"Ad Alpha Church",
    "italoGoncalves":"Italo Gonçalves",
    "jazinho":"Jazinho",
    "klefersonOliveira":"Kleferson de Oliveira",
    "lucasBlumer":"Lucas Blumer",
    "paschoalPiragine":"Paschoal Piragine",
    "lucianoManga":"Luciano Manga",
    "realityXP":"RealityXP",
    "itaqueraChurch":"Itaquera Church",
    "isabellaGaspary":"Isabella Gaspary",
    "gustavoTV":"GustavoTV",
    "oficialIbab":"IBAB",
    "familyPlays":"Family Plays",
    "anaEOsGamers":"Ana e os Gamers",
    "joaoKepler":"João Kepler",
    "cristianismoSemFronteiras":"Cristianismo Sem Fronteiras",
    "luzParaOCaminho":"Luz Para o Caminho",
    "oitava":"Oitava Igreja Presbiteriana BH",
    "flamarion":"Pr. Flamarion",
    "lagoinha":"Lagoinha",
    "vidaVerde":"Vida Verde Sistemas Sustentáveis",
    "miranteNews":"Mirante News FM",
    "adrenalinaPuraLatam":"Adrenalina Pura TV Latam",
    "filmelierLatam":"Filmelier TV Latam",
    "adrenalinaPuraBR":"Adrenalina Pura TV BR",
    "filmelierBR":"Filmelier TV BR",
    "imirante":"Imirante.com",
    "nickVujicic":"Nick Vujicic",
    "silasMalafaia":"Silas Malafaia Oficial",
    "elizeteMalafaia":"Elizete Malafaia",
    "afterPodcast":"After Podcast",
    "itatiaiaPop":"Itatiaia Pop",
    "queroAprender":"Quero Aprender - Samuel Lima",
    "miranteFM":"Mirante FM",
    "bahiaNoticias":"Bahia Notícias",
    "tvAparecidaAtual":"TV Aparecida",
    "leoFigueiredo":"Leo Figueiredo",
    "ulissesTV":"Ulisses TV",
    "oTempoLivre":"O Tempo Livre",
    "3Palavrinhas":"3 Palavrinhas",
    "3LittleWords":"3 Little Words",
    "3LittleWordsBaby":"3 Little Words Baby",
    "hermannGreb":"Hermann Greb",
    "aventurasDeTUC":"Aventuras De TUC",
    "diima":"Diima",
    "lagoinhaOne":"Lagoinha One",
    "jonBirolo":"Jon Birolo",
    "felipeSilvattos":"Felipe Silvattos",
    "rebecaKids":"Rebeca Kids",
    "smilinguido":"Smilinguido",
    "3PalavrinhasReact":"3 Palavrinhas React",
    "laatus":"Laatus",
    "tribunaDoLeste":"Tribuna do Leste",
    "lofiWork":"Lofi Work Music",
    "tvGreen":"TV Green",
    "ICTV":"ICTV",
    "tvAparecida_Setembro":"TV Aparecida",
    "revistaOeste":"Revista Oeste"
}